matin/__init__.py
matin/arial.ttf
matin/gpus.py
matin/pen.py
matin/picasso.py
matin-0.1.dist-info/LICENSE
matin-0.1.dist-info/METADATA
matin-0.1.dist-info/WHEEL
matin-0.1.dist-info/top_level.txt
matin-0.1.dist-info/RECORD
