Metadata-Version: 2.1
Name: matin
Version: 0.1
Summary: A handy formatter for matplotlib
Home-page: http://www.example.com/~cschultz/bvote/
Author: anonymous
Author-email: anonymous@anonymous.com
Project-URL: Bug Tracker, http://bitbucket.org/tarek/distribute/issues/
Classifier: Programming Language :: Python :: 3
Classifier: License :: OSI Approved :: MIT License
Classifier: Operating System :: OS Independent
Requires-Python: >=3.6
License-File: LICENSE
Requires-Dist: matplotlib
